sopel_url/__init__.py
sopel_url/backend.py
sopel_url/config.py
sopel_url/plugin.py
sopel_url-1.0.0.dist-info/licenses/LICENSE.txt
sopel_url-1.0.0.dist-info/METADATA
sopel_url-1.0.0.dist-info/WHEEL
sopel_url-1.0.0.dist-info/entry_points.txt
sopel_url-1.0.0.dist-info/top_level.txt
sopel_url-1.0.0.dist-info/RECORD
