Metadata-Version: 2.4
Name: sopel-url
Version: 1.0.0
Summary: URL auto title plugin for Sopel
Author-email: dgw <dgw@technobabbl.es>, Florian Strzelecki <florian.strzelecki@gmail.com>
Maintainer-email: Florian Strzelecki <florian.strzelecki@gmail.com>
License: EFL-2.0
Project-URL: Homepage, https://github.com/sopel-irc/sopel-url
Project-URL: Bug Tracker, https://github.com/sopel-irc/sopel-url/issues
Keywords: sopel,plugin,http,bot,irc
Platform: Linux x86, x86-64
Classifier: Development Status :: 5 - Production/Stable
Classifier: Intended Audience :: Developers
Classifier: Intended Audience :: System Administrators
Classifier: Operating System :: POSIX :: Linux
Classifier: Programming Language :: Python :: 3.8
Classifier: Programming Language :: Python :: 3.9
Classifier: Programming Language :: Python :: 3.10
Classifier: Programming Language :: Python :: 3.11
Classifier: Programming Language :: Python :: 3.12
Classifier: Programming Language :: Python :: 3.13
Classifier: Topic :: Communications :: Chat :: Internet Relay Chat
Requires-Python: <4,>=3.7
License-File: LICENSE.txt
Requires-Dist: sopel>=8.0
Requires-Dist: requests
Dynamic: license-file
